vlmc-0.2.0.dist-info/METADATA
vlmc-0.2.0.dist-info/WHEEL
vlmc/__init__.py
vlmc/vlmc.abi3.so
vlmc-0.2.0.dist-info/RECORD
