Metadata-Version: 2.1
Name: vlmc
Version: 0.2.0
Summary: Variable Length Markov Chain
Author-email: António Leitão <aleitao@novaims.unl.pt>
Requires-Python: >=3.10
Project-URL: repository, https://github.com/antonio-leitao/vlmc
Project-URL: homepage, https://github.com/antonio-leitao/vlmc
